redisio/__init__.py
redisio/redisio.py
redisio-0.7.dist-info/METADATA
redisio-0.7.dist-info/RECORD
redisio-0.7.dist-info/WHEEL
redisio-0.7.dist-info/top_level.txt
