Metadata-Version: 2.1
Name: redisio
Version: 0.7
Summary: A tiny redis client for script boys with high performance. Optimized especially for massive insertion.
Home-page: https://github.com/cf020031308/redisio
Author: Roy
Author-email: cf020031308@163.com
Maintainer: Roy
Maintainer-email: cf020031308@163.com
License: MIT
Keywords: Redis,key-value store
Platform: UNKNOWN
Classifier: Development Status :: 5 - Production/Stable
Classifier: Intended Audience :: Developers
Classifier: License :: OSI Approved :: MIT License
Classifier: Programming Language :: Python :: 2.7
Classifier: Programming Language :: Python :: 3
Classifier: Topic :: Database
